hummingsim-20190724.dist-info/RECORD
hummingsim-20190724.dist-info/METADATA
hummingsim-20190724.dist-info/top_level.txt
hummingsim-20190724.dist-info/WHEEL
hummingsim/__init__.py
hummingsim/strategy/unit_test_strategy.cpython-36m-x86_64-linux-gnu.so
hummingsim/strategy/print_out_strategy.cpython-36m-x86_64-linux-gnu.so
hummingsim/backtest/ddex_order_book_loader.cpython-36m-x86_64-linux-gnu.so
hummingsim/backtest/wallet_data.py
hummingsim/backtest/radar_relay_order_book_loader.cpython-36m-x86_64-linux-gnu.so
hummingsim/backtest/mock_order_book_loader.cpython-36m-x86_64-linux-gnu.so
hummingsim/backtest/market_config.py
hummingsim/backtest/composite_order_book.cpython-36m-x86_64-linux-gnu.so
hummingsim/backtest/bittrex_order_book_loader.cpython-36m-x86_64-linux-gnu.so
hummingsim/backtest/order_book_loader.cpython-36m-x86_64-linux-gnu.so
hummingsim/backtest/binance_order_book_loader_v2.cpython-36m-x86_64-linux-gnu.so
hummingsim/backtest/order_book_loader_base.cpython-36m-x86_64-linux-gnu.so
hummingsim/backtest/backtest_market.cpython-36m-x86_64-linux-gnu.so
hummingsim/backtest/staging_account_manager.cpython-36m-x86_64-linux-gnu.so
hummingsim/backtest/staging_market.cpython-36m-x86_64-linux-gnu.so
hummingsim/backtest/huobi_order_book_loader.cpython-36m-x86_64-linux-gnu.so
hummingsim/backtest/__init__.py
hummingsim/backtest/backtest_account_manager.cpython-36m-x86_64-linux-gnu.so
hummingsim/backtest/market_account_manager_base.cpython-36m-x86_64-linux-gnu.so
hummingsim/backtest/market.cpython-36m-x86_64-linux-gnu.so
hummingsim/backtest/wallet.cpython-36m-x86_64-linux-gnu.so
hummingsim/backtest/external_order_book_data.cpython-36m-x86_64-linux-gnu.so
hummingsim/model/asset.py
hummingsim/model/sql_keep_alive.cpython-36m-x86_64-linux-gnu.so
hummingsim/model/market_withdraw_rules.py
hummingsim/model/sql_connection_manager.py
hummingsim/model/market_data.py
hummingsim/model/backtest_account.py
hummingsim/model/__init__.py
hummingsim/model/backtest_account_asset.py
