Metadata-Version: 2.1
Name: hummingsim
Version: 20190724
Summary: CoinAlpha Hummingsim
Home-page: https://github.com/CoinAlpha/hummingsim
Author: Martin Kou
Author-email: martin@coinalpha.com
License: Proprietary
Platform: UNKNOWN
Requires-Dist: aioconsole
Requires-Dist: aiokafka
Requires-Dist: cytoolz
Requires-Dist: kafka-python
Requires-Dist: lru-dict
Requires-Dist: parsimonious
Requires-Dist: pycryptodome
Requires-Dist: requests
Requires-Dist: rlp
Requires-Dist: toolz
Requires-Dist: tzlocal
Requires-Dist: urllib3
Requires-Dist: websockets
Requires-Dist: aiohttp
Requires-Dist: async-timeout
Requires-Dist: attrs
Requires-Dist: certifi
Requires-Dist: chardet
Requires-Dist: cython (==0.29.5)
Requires-Dist: idna
Requires-Dist: idna-ssl
Requires-Dist: multidict
Requires-Dist: numpy
Requires-Dist: pandas
Requires-Dist: pytz
Requires-Dist: pyyaml
Requires-Dist: sqlalchemy
Requires-Dist: ujson
Requires-Dist: yarl
